<?xml version="1.0"?>
<Configuration xmlns="http://www.jdiameter.org/jdiameter-server">

	<LocalPeer>
		<URI value="aaa://127.0.0.1:3868" />

		<IPAddresses>
			<IPAddress value="127.0.0.1" />
		</IPAddresses>
		<Realm value="exchange.example.org" />
		<VendorID value="0" />
		<ProductName value="jDiameter" />
		<FirmwareRevision value="1" />
		<OverloadMonitor>
			<Entry index="1" lowThreshold="0.5" highThreshold="0.6">
				<ApplicationID>
					<VendorId value="0" />
					<AuthApplId value="16777251" />
					<AcctApplId value="0" />
				</ApplicationID>
			</Entry>
		</OverloadMonitor>
		
	</LocalPeer>

	<Parameters>
		<!-- set to true, we can safely remove client def in this case -->
		<AcceptUndefinedPeer value="true" />
		<DuplicateProtection value="true" />
		<DuplicateTimer value="240000" />
		<UseUriAsFqdn value="false" />
		<QueueSize value="10000" />
		<MessageTimeOut value="60000" />
		<StopTimeOut value="10000" />
		<CeaTimeOut value="10000" />
		<IacTimeOut value="30000" />
		<DwaTimeOut value="10000" />
		<DpaTimeOut value="5000" />
		<RecTimeOut value="10000" />
		<Concurrent>
			<Entity name="ThreadGroup" size="64" />
			<Entity name="ProcessingMessageTimer" size="1" />
			<Entity name="DuplicationMessageTimer" size="1" />
			<Entity name="RedirectMessageTimer" size="1" />
			<Entity name="PeerOverloadTimer" size="1" />
			<Entity name="ConnectionTimer" size="1" />
			<Entity name="StatisticTimer" size="1" />
		</Concurrent>

	</Parameters>

	<Network>
		<Peers>
			<!-- our client, lets define it -->
			<Peer name="aaa://127.0.0.1:13869" portRange="3868-3868" attempt_connect="false"
				rating="1" />

		</Peers>
		<Realms>
			<Realm name="exchange.example.org" peers="127.0.0.1" local_action="LOCAL" dynamic="false" exp_time="1">
				<ApplicationID>
					<VendorId value="0" />
					<AuthApplId value="16777251" />
					<AcctApplId value="0" />
				</ApplicationID>
			</Realm>
                        
                        <Realm name="honeypot.example.org" peers="127.0.0.1" local_action="LOCAL" dynamic="false" exp_time="1">
				<ApplicationID>
					<VendorId value="0" />
					<AuthApplId value="16777251" />
					<AcctApplId value="0" />
				</ApplicationID>
			</Realm>


		</Realms>
	</Network>

	<Extensions>
            <!-- Set SCTP classes as extension points for Connection and Network Guard -->
            <Connection value="org.jdiameter.client.impl.transport.sctp.SCTPClientConnection" />
            <NetworkGuard value="org.jdiameter.server.impl.io.sctp.NetworkGuard" />
        </Extensions>

</Configuration>
